ornexus/__init__.py
ornexus/cli.py
ornexus/database.py
ornexus/main.py
ornexus/config/agents.yaml
ornexus/config/tasks.yaml
ornexus/deploy/install_api_structure.sh
ornexus/knowledge/__init__.py
ornexus/utils/__init__.py
ornexus/utils/agent_manager.py
ornexus/utils/agent_registry.py
ornexus/utils/config_utils.py
ornexus-0.2.29.dist-info/licenses/LICENSE
ornexus-0.2.29.dist-info/METADATA
ornexus-0.2.29.dist-info/WHEEL
ornexus-0.2.29.dist-info/entry_points.txt
ornexus-0.2.29.dist-info/top_level.txt
ornexus-0.2.29.dist-info/RECORD
