Metadata-Version: 2.4
Name: ornexus
Version: 0.2.29
Summary: Framework para criação de agentes com Agno
Home-page: https://github.com/luandetoni/ornexus
Author: OrNexus
Author-email: contato@ornexus.com
Classifier: Programming Language :: Python :: 3
Classifier: License :: OSI Approved :: MIT License
Classifier: Operating System :: OS Independent
Requires-Python: >=3.8
License-File: LICENSE
Provides-Extra: agno
Requires-Dist: agno; extra == "agno"
Requires-Dist: pymongo; extra == "agno"
Requires-Dist: openai; extra == "agno"
Requires-Dist: motor; extra == "agno"
Requires-Dist: python-dotenv; extra == "agno"
Provides-Extra: crewai
Requires-Dist: crewai[tools]; extra == "crewai"
Requires-Dist: pymongo; extra == "crewai"
Requires-Dist: motor; extra == "crewai"
Requires-Dist: python-dotenv; extra == "crewai"
Provides-Extra: all
Requires-Dist: agno; extra == "all"
Requires-Dist: pymongo; extra == "all"
Requires-Dist: openai; extra == "all"
Requires-Dist: crewai[tools]; extra == "all"
Requires-Dist: motor; extra == "all"
Requires-Dist: python-dotenv; extra == "all"
Dynamic: license-file
